awslogs/__init__.py
awslogs/__main__.py
zmunk_awslogs-1.0.2.dist-info/licenses/LICENSE
zmunk_awslogs-1.0.2.dist-info/METADATA
zmunk_awslogs-1.0.2.dist-info/WHEEL
zmunk_awslogs-1.0.2.dist-info/top_level.txt
zmunk_awslogs-1.0.2.dist-info/RECORD
