Metadata-Version: 2.4
Name: zmunk-awslogs
Version: 1.0.2
Summary: CLI-friendly AWS log viewer
Author-email: zmunk <ibrahim.tigrek@gmail.com>
License: MIT License
Project-URL: Homepage, https://github.com/zmunk/awslogs
Keywords: aws,boto3,logs,cloudwatch,lambda
Classifier: License :: OSI Approved :: MIT License
Classifier: Programming Language :: Python
Classifier: Programming Language :: Python :: 3
Requires-Python: >=3.10
License-File: LICENSE
Requires-Dist: boto3
Dynamic: license-file
